ohh/__init__.py
ohh/background_runner.py
ohh/cli.py
ohh/daemon.py
ohh/runner.py
ohh/shell_completion.py
ohh-0.7.1.data/scripts/ohh
ohh-0.7.1.dist-info/LICENSE
ohh-0.7.1.dist-info/METADATA
ohh-0.7.1.dist-info/WHEEL
ohh-0.7.1.dist-info/top_level.txt
ohh-0.7.1.dist-info/RECORD
