Metadata-Version: 2.1
Name: ohh
Version: 0.7.1
Summary: CLI tool for OHH project
Home-page: https://git.claudetech.com/ohh/ohh-cli
Author: Daniel Perez
Author-email: daniel@claudetech.com
License: UNKNOWN
Platform: UNKNOWN
Classifier: Development Status :: 2 - Pre-Alpha
Classifier: Programming Language :: Python
Classifier: Programming Language :: Python :: 2
Classifier: Programming Language :: Python :: 2.7
Classifier: Programming Language :: Python :: 3
Classifier: Programming Language :: Python :: 3.3
Requires-Dist: requests
Requires-Dist: psutil
Requires-Dist: python-dateutil
Requires-Dist: pync
